mcons/__init__.py
mcons/check_depend.py
mcons/compile_commands.py
mcons/config.py
mcons/cons_module.py
mcons/env.py
mcons/object_rule.py
mcons/record_dict.py
mcons/rule.py
mcons/run_build.py
mcons/run_clean.py
mcons/run_init.py
mcons/run_mode.py
mcons/run_watch.py
mcons/task.py
mcons/thread_pool.py
mcons/utils.py
mcons-1.0.4.dist-info/LICENSE
mcons-1.0.4.dist-info/METADATA
mcons-1.0.4.dist-info/WHEEL
mcons-1.0.4.dist-info/top_level.txt
mcons-1.0.4.dist-info/RECORD
