Metadata-Version: 2.1
Name: mcons
Version: 1.0.4
Summary: a project building tool
Classifier: Programming Language :: Python :: 3
Classifier: License :: OSI Approved :: MIT License
License-File: LICENSE
Requires-Dist: PyYAML
Requires-Dist: watchact
